verilog/Alu.v
module Alu(
input clk, reset,
input [4:0] aluFN,
input [BIT_WIDTH-1:0] in1, in2,
output reg [BIT_WIDTH-1:0] out
);

parameter BIT_WIDTH = 32;

localparam ADD  = 5'b00011;
localparam SUB  = 5'b00010;
localparam AND  = 5'b00111;
localparam OR   = 5'b00110;
localparam XOR  = 5'b00101;
localparam NAND = 5'b01011;
localparam NOR  = 5'b01010;
localparam XNOR = 5'b01001;

localparam F   = 5'b10011;
localparam EQ  = 5'b11100;
localparam LT  = 5'b11101;
localparam LTE = 5'b10010;
localparam T   = 5'b11111;
localparam NE  = 5'b10000;
localparam GTE = 5'b10001;
localparam GT  = 5'b11110;

always @(*) begin
    case (aluFN)
        ADD  : out <= in1 + in2;
        SUB  : out <= in1 - in2;
        AND  : out <= in1 & in2;
        OR   : out <= in1 | in2;
        XOR  : out <= in1 ^ in2;
        NAND : out <= in1 ~& in2;
        NOR  : out <= in1 ~| in2;
        XNOR : out <= in1 ~^ in2;

        F    : out <= 0;
        EQ   : out <= (in1 == in2) ? 1 : 0;
        LT   : out <= (in1 < in2) ? 1 : 0;
        LTE  : out <= (in1 <= in2) ? 1 : 0;
        T    : out <= 1;
        NE   : out <= (in1 != in2) ? 1 : 0;
        GTE  : out <= (in1 >= in2) ? 1 : 0;
        GT   : out <= (in1 > in2) ? 1 : 0;
        default : out <= 0;
    endcase
end

endmodule

verilog/Mux4to1.v
module Mux4to1(
input clk, reset,
input [1:0] select,
input [BIT_WIDTH-1:0] in0, in1, in2, in3,
output reg [BIT_WIDTH-1:0] out
);

parameter BIT_WIDTH = 32;

always @(*) begin
    case (select)
        0: out <= in0;
        1: out <= in1;
        2: out <= in2;
        3: out <= in3;
        default: out <= 32'hzzzzzzzz; // TODO: FIX so BIT_WIDTH
    endcase
end

endmodule

verilog/SignExtension.v
module SignExtension(dIn, dOut);
  parameter IN_BIT_WIDTH = 16;
  parameter OUT_BIT_WIDTH = 32;

  input [(IN_BIT_WIDTH-1):0]  dIn;
  output[(OUT_BIT_WIDTH-1):0] dOut;

  assign dOut = {{(OUT_BIT_WIDTH - IN_BIT_WIDTH){dIn[IN_BIT_WIDTH-1]}}, dIn};
endmodule

verilog/Register.v
`ifndef _REGISTER_
`define _REGISTER_

module Register(
input clk, reset, en_write,
input[BIT_WIDTH - 1: 0] data_in,
output reg [BIT_WIDTH - 1: 0] data_out
);

parameter BIT_WIDTH = 32;
parameter RESET_VALUE = 0;

always @(posedge clk) begin
    if (reset == 1'b1)
        data_out <= RESET_VALUE;
    else if (en_write == 1'b1)
        data_out <= data_in;
end

endmodule

`endif

verilog/RegisterFile.v
`include "Register.v"

module RegisterFile(
input clk, reset, en_write,
input [REG_INDEX_WIDTH-1:0] sr1_ind, sr2_ind, dr_ind,
input [BIT_WIDTH-1:0] data_in,
output [BIT_WIDTH-1:0] sr1, sr2
);

parameter BIT_WIDTH = 32;
parameter REG_INDEX_WIDTH = 4;
parameter RESET_VALUE = 0;

wire [BIT_WIDTH-1:0] reg_data_out [(1<<REG_INDEX_WIDTH)-1:0];

genvar i;
generate
    for (i=0; i<(1<<REG_INDEX_WIDTH); i=i+1) begin
        wire en_write1;
        Register #(
            .BIT_WIDTH(BIT_WIDTH), .RESET_VALUE(RESET_VALUE)
            ) regs (
            .clk (clk),
            .reset (reset),
            .en_write (en_write1),
            .data_in (data_in),
            .data_out (reg_data_out[i])
            );
        assign en_write1 = (dr_ind == i) ? en_write : 0;
    end
endgenerate


assign sr1 = reg_data_out[sr1_ind];
assign sr2 = reg_data_out[sr2_ind];

endmodule

verilog/Decoder.v
module Decoder(
input clk, reset,
input [DATA_BIT_WIDTH-1:0] data,
output reg [4:0] aluFN,
output reg [REG_INDEX_WIDTH-1:0] src_reg1, src_reg2, dest_reg,
output reg [IMM_BIT_WIDTH-1:0] imm,
output reg [1:0] aluSrc2Sel,
output reg wr_en
);

localparam REG_INDEX_WIDTH = 4;
localparam DATA_BIT_WIDTH = 32;
localparam IMM_BIT_WIDTH = 16;

localparam OP1_ALUR  = 4'b1111;
localparam OP1_ALUI  = 4'b1011;
localparam OP1_CMPR  = 4'b1110;
localparam OP1_CMPI  = 4'b1010;
// localparam OP1_BCOND = 4'b0000;
// localparam OP1_SW    = 4'b1001;
// localparam OP1_LW    = 4'b1000;
// localparam OP1_JAL   = 4'b0001;

wire [3:0] fn;
wire [3:0] opcode;

assign fn = data[31:28];
assign opcode = data[27:24];

always @(*) begin
    src_reg1 <= data[7:4];
    src_reg2 <= data[11:8];
    dest_reg <= data[3:0];
    imm <= data[23:8];
    wr_en = 1'b1;
end

always @(*) begin
    case (opcode)
        OP1_ALUR: begin
            aluFN <= {1'b0, fn};
            aluSrc2Sel <= 2'b00;
        end
        OP1_ALUI: begin
            aluFN <= {1'b0, fn};
            aluSrc2Sel <= 2'b01;
        end
        OP1_CMPR: begin
            aluFN <= {1'b1, fn};
            aluSrc2Sel <= 2'b00;
        end
        OP1_CMPI: begin
            aluFN <= {1'b1, fn};
            aluSrc2Sel <= 2'b01;
        end
        default: begin
            aluFN <= 5'bzzzzz;
            aluSrc2Sel <= 2'bzz;
        end
    endcase
end

endmodule

verilog/InstMemory.v
module InstMemory(
input[ADDR_BIT_WIDTH - 1: 0] addr,
output[DATA_BIT_WIDTH - 1: 0] dataOut
);

parameter MEM_INIT_FILE = "";
parameter ADDR_BIT_WIDTH = 11;
parameter DATA_BIT_WIDTH = 32;
parameter N_WORDS = (1 << ADDR_BIT_WIDTH);

(* ram_init_file = MEM_INIT_FILE *)
// initial begin
// 	$readmemh("test.hex", data);
// end

reg [15:0] test1;
reg[DATA_BIT_WIDTH - 1: 0] data[0: N_WORDS - 1];

assign dataOut = data[addr];

endmodule

verilog/Processor.v
`include "Alu.v"
`include "Decoder.v"
`include "InstMemory.v"
`include "Mux4to1.v"
`include "Register.v"
`include "RegisterFile.v"
`include "SignExtension.v"

module Processor (
input clk,
input reset,
output [IMEM_DATA_BIT_WIDTH - 1: 0] inst_word_out // For testing
);

parameter DBITS                 = 32;
parameter IMEM_INIT_FILE        = "Sorter2.mif";

localparam INST_SIZE             = 32'd4;
localparam INST_BIT_WIDTH        = 32;
localparam START_PC              = 32'h40;
localparam REG_INDEX_BIT_WIDTH   = 4;

localparam IMEM_ADDR_BIT_WIDTH   = 11;
localparam IMEM_DATA_BIT_WIDTH   = INST_BIT_WIDTH;
localparam IMEM_PC_BITS_HI       = IMEM_ADDR_BIT_WIDTH + 2;
localparam IMEM_PC_BITS_LO       = 2;

// Create PC and its logic
wire pcWrtEn = 1'b1;
reg [DBITS - 1: 0] pcIn;
wire [DBITS - 1: 0] pcOut;

Register #(
    .BIT_WIDTH(DBITS), .RESET_VALUE(START_PC)
    ) pc (
    clk, reset, pcWrtEn, pcIn, pcOut
);

always @(*) begin
    if (instWord == 32'h0000DEAD) begin
        pcIn <= pcOut;
        // $finish;
    end else begin
        pcIn <= pcOut + 4;
    end
end

assign inst_word_out = instWord;

// assign pcIn = (instWord != 32'h0000DEAD) ? pcOut + 4 : pcOut;

wire [IMEM_DATA_BIT_WIDTH - 1: 0] instWord;
InstMemory #(
    IMEM_INIT_FILE,
    IMEM_ADDR_BIT_WIDTH,
    IMEM_DATA_BIT_WIDTH
    ) instMem (
    .addr (pcOut[IMEM_PC_BITS_HI - 1: IMEM_PC_BITS_LO]),
    .dataOut (instWord)
);

wire [4:0] aluFN;
wire [3:0] src_reg1, src_reg2, dest_reg;
wire [15:0] imm;
wire [1:0] aluSrc2Sel;
wire wr_en;
Decoder decoder (
    .clk (clk),
    .reset (reset),
    .data (instWord),
    .aluFN (aluFN),
    .src_reg1 (src_reg1),
    .src_reg2 (src_reg2),
    .dest_reg (dest_reg),
    .imm (imm),
    .aluSrc2Sel (aluSrc2Sel),
    .wr_en (wr_en)
);

wire [DBITS-1:0] alu_out, regs_out1, regs_out2;
wire reg_write;

assign reg_write = 1'b1;

RegisterFile #(
    .BIT_WIDTH (DBITS),
    .REG_INDEX_WIDTH (REG_INDEX_BIT_WIDTH),
    .RESET_VALUE (0)
    ) regs (
    .clk (clk),
    .reset (reset),
    .en_write (reg_write),
    .sr1_ind (src_reg1),
    .sr2_ind (src_reg2),
    .dr_ind (dest_reg),
    .data_in (alu_out),
    .sr1 (regs_out1),
    .sr2 (regs_out2)
);

wire [DBITS-1:0] imm_ext;
SignExtension #(
    .IN_BIT_WIDTH (16),
    .OUT_BIT_WIDTH (DBITS)
    ) sign_extend (
    .dIn (imm),
    .dOut (imm_ext)
);

wire [DBITS-1:0] alu_in2;
Mux4to1 #(
    .BIT_WIDTH (DBITS)
    ) alu_in2_mux (
    .clk (clk),
    .reset (reset),
    .select (aluSrc2Sel),
    .in0 (regs_out2),
    .in1 (imm_ext),
    .in2 (32'hzzzzzzzz),
    .in3 (32'hzzzzzzzz),
    .out (alu_in2)
);

Alu #(
    .BIT_WIDTH (DBITS)
    ) alu (
    .clk (clk),
    .reset (reset),
    .aluFN (aluFN),
    .in1 (regs_out1),
    .in2 (alu_in2),
    .out (alu_out)
);

endmodule

verilog/testbenches/Processor_tb.v
`timescale 1ns/1ps

`include "Processor.v"

module Processor_tb;

parameter DBITS = 32;

reg clk, reset;
wire [DBITS-1:0] instr_word;

Processor #(
    .DBITS (DBITS),
    .IMEM_INIT_FILE ("test.mif")
    ) processor (
    .clk (clk),
    .reset (reset),
    .inst_word_out (instr_word)
);

initial begin
    $readmemh("../../assembly-files/test.hex", processor.instMem.data);
    $dumpfile("Processor.vcd");
    $dumpvars(0, Processor_tb);
end

initial begin
    reset <= 0;
    clk <= 0;
    @(posedge clk);
    reset <= 1;
    @(posedge clk);
    reset <= 0;
    @(posedge clk);

    @(instr_word == 32'h0000DEAD);
    @(posedge clk);
    @(posedge clk);
    $finish;

    // @(posedge clk);
    // @(posedge clk);
    // @(posedge clk);
    // @(posedge clk);
    // @(posedge clk);
    // @(posedge clk);
    // @(posedge clk);
    // @(posedge clk);
    //
    // $finish;
end

always #10 clk = ~clk;

endmodule

verilog/testbenches/Processor.vcd
$date
	Sat Nov 11 22:09:44 2017
$end
$version
	Icarus Verilog
$end
$timescale
	1ps
$end
$scope module Processor_tb $end
$var wire 32 ! instr_word [31:0] $end
$var reg 1 " clk $end
$var reg 1 # reset $end
$scope module processor $end
$var wire 1 " clk $end
$var wire 32 $ inst_word_out [31:0] $end
$var wire 1 % pcWrtEn $end
$var wire 1 & reg_write $end
$var wire 1 # reset $end
$var wire 1 ' wr_en $end
$var wire 4 ( src_reg2 [3:0] $end
$var wire 4 ) src_reg1 [3:0] $end
$var wire 32 * regs_out2 [31:0] $end
$var wire 32 + regs_out1 [31:0] $end
$var wire 32 , pcOut [31:0] $end
$var wire 32 - instWord [31:0] $end
$var wire 32 . imm_ext [31:0] $end
$var wire 16 / imm [15:0] $end
$var wire 4 0 dest_reg [3:0] $end
$var wire 32 1 alu_out [31:0] $end
$var wire 32 2 alu_in2 [31:0] $end
$var wire 2 3 aluSrc2Sel [1:0] $end
$var wire 5 4 aluFN [4:0] $end
$var reg 32 5 pcIn [31:0] $end
$scope module alu $end
$var wire 1 " clk $end
$var wire 1 # reset $end
$var wire 32 6 in2 [31:0] $end
$var wire 32 7 in1 [31:0] $end
$var wire 5 8 aluFN [4:0] $end
$var reg 32 9 out [31:0] $end
$upscope $end
$scope module alu_in2_mux $end
$var wire 1 " clk $end
$var wire 32 : in2 [31:0] $end
$var wire 32 ; in3 [31:0] $end
$var wire 1 # reset $end
$var wire 2 < select [1:0] $end
$var wire 32 = in1 [31:0] $end
$var wire 32 > in0 [31:0] $end
$var reg 32 ? out [31:0] $end
$upscope $end
$scope module decoder $end
$var wire 1 " clk $end
$var wire 1 # reset $end
$var wire 4 @ opcode [3:0] $end
$var wire 4 A fn [3:0] $end
$var wire 32 B data [31:0] $end
$var reg 5 C aluFN [4:0] $end
$var reg 2 D aluSrc2Sel [1:0] $end
$var reg 4 E dest_reg [3:0] $end
$var reg 16 F imm [15:0] $end
$var reg 4 G src_reg1 [3:0] $end
$var reg 4 H src_reg2 [3:0] $end
$var reg 1 ' wr_en $end
$upscope $end
$scope module instMem $end
$var wire 11 I addr [10:0] $end
$var wire 32 J dataOut [31:0] $end
$upscope $end
$scope module pc $end
$var wire 1 " clk $end
$var wire 32 K data_in [31:0] $end
$var wire 1 % en_write $end
$var wire 1 # reset $end
$var reg 32 L data_out [31:0] $end
$upscope $end
$scope module regs $end
$var wire 1 " clk $end
$var wire 32 M data_in [31:0] $end
$var wire 4 N dr_ind [3:0] $end
$var wire 1 & en_write $end
$var wire 1 # reset $end
$var wire 32 O sr1 [31:0] $end
$var wire 4 P sr1_ind [3:0] $end
$var wire 32 Q sr2 [31:0] $end
$var wire 4 R sr2_ind [3:0] $end
$scope begin genblk1[0] $end
$var wire 1 S en_write1 $end
$scope module regs $end
$var wire 1 " clk $end
$var wire 32 T data_in [31:0] $end
$var wire 1 S en_write $end
$var wire 1 # reset $end
$var reg 32 U data_out [31:0] $end
$upscope $end
$upscope $end
$scope begin genblk1[1] $end
$var wire 1 V en_write1 $end
$scope module regs $end
$var wire 1 " clk $end
$var wire 32 W data_in [31:0] $end
$var wire 1 V en_write $end
$var wire 1 # reset $end
$var reg 32 X data_out [31:0] $end
$upscope $end
$upscope $end
$scope begin genblk1[2] $end
$var wire 1 Y en_write1 $end
$scope module regs $end
$var wire 1 " clk $end
$var wire 32 Z data_in [31:0] $end
$var wire 1 Y en_write $end
$var wire 1 # reset $end
$var reg 32 [ data_out [31:0] $end
$upscope $end
$upscope $end
$scope begin genblk1[3] $end
$var wire 1 \ en_write1 $end
$scope module regs $end
$var wire 1 " clk $end
$var wire 32 ] data_in [31:0] $end
$var wire 1 \ en_write $end
$var wire 1 # reset $end
$var reg 32 ^ data_out [31:0] $end
$upscope $end
$upscope $end
$scope begin genblk1[4] $end
$var wire 1 _ en_write1 $end
$scope module regs $end
$var wire 1 " clk $end
$var wire 32 ` data_in [31:0] $end
$var wire 1 _ en_write $end
$var wire 1 # reset $end
$var reg 32 a data_out [31:0] $end
$upscope $end
$upscope $end
$scope begin genblk1[5] $end
$var wire 1 b en_write1 $end
$scope module regs $end
$var wire 1 " clk $end
$var wire 32 c data_in [31:0] $end
$var wire 1 b en_write $end
$var wire 1 # reset $end
$var reg 32 d data_out [31:0] $end
$upscope $end
$upscope $end
$scope begin genblk1[6] $end
$var wire 1 e en_write1 $end
$scope module regs $end
$var wire 1 " clk $end
$var wire 32 f data_in [31:0] $end
$var wire 1 e en_write $end
$var wire 1 # reset $end
$var reg 32 g data_out [31:0] $end
$upscope $end
$upscope $end
$scope begin genblk1[7] $end
$var wire 1 h en_write1 $end
$scope module regs $end
$var wire 1 " clk $end
$var wire 32 i data_in [31:0] $end
$var wire 1 h en_write $end
$var wire 1 # reset $end
$var reg 32 j data_out [31:0] $end
$upscope $end
$upscope $end
$scope begin genblk1[8] $end
$var wire 1 k en_write1 $end
$scope module regs $end
$var wire 1 " clk $end
$var wire 32 l data_in [31:0] $end
$var wire 1 k en_write $end
$var wire 1 # reset $end
$var reg 32 m data_out [31:0] $end
$upscope $end
$upscope $end
$scope begin genblk1[9] $end
$var wire 1 n en_write1 $end
$scope module regs $end
$var wire 1 " clk $end
$var wire 32 o data_in [31:0] $end
$var wire 1 n en_write $end
$var wire 1 # reset $end
$var reg 32 p data_out [31:0] $end
$upscope $end
$upscope $end
$scope begin genblk1[10] $end
$var wire 1 q en_write1 $end
$scope module regs $end
$var wire 1 " clk $end
$var wire 32 r data_in [31:0] $end
$var wire 1 q en_write $end
$var wire 1 # reset $end
$var reg 32 s data_out [31:0] $end
$upscope $end
$upscope $end
$scope begin genblk1[11] $end
$var wire 1 t en_write1 $end
$scope module regs $end
$var wire 1 " clk $end
$var wire 32 u data_in [31:0] $end
$var wire 1 t en_write $end
$var wire 1 # reset $end
$var reg 32 v data_out [31:0] $end
$upscope $end
$upscope $end
$scope begin genblk1[12] $end
$var wire 1 w en_write1 $end
$scope module regs $end
$var wire 1 " clk $end
$var wire 32 x data_in [31:0] $end
$var wire 1 w en_write $end
$var wire 1 # reset $end
$var reg 32 y data_out [31:0] $end
$upscope $end
$upscope $end
$scope begin genblk1[13] $end
$var wire 1 z en_write1 $end
$scope module regs $end
$var wire 1 " clk $end
$var wire 32 { data_in [31:0] $end
$var wire 1 z en_write $end
$var wire 1 # reset $end
$var reg 32 | data_out [31:0] $end
$upscope $end
$upscope $end
$scope begin genblk1[14] $end
$var wire 1 } en_write1 $end
$scope module regs $end
$var wire 1 " clk $end
$var wire 32 ~ data_in [31:0] $end
$var wire 1 } en_write $end
$var wire 1 # reset $end
$var reg 32 !" data_out [31:0] $end
$upscope $end
$upscope $end
$scope begin genblk1[15] $end
$var wire 1 "" en_write1 $end
$scope module regs $end
$var wire 1 " clk $end
$var wire 32 #" data_in [31:0] $end
$var wire 1 "" en_write $end
$var wire 1 # reset $end
$var reg 32 $" data_out [31:0] $end
$upscope $end
$upscope $end
$upscope $end
$scope module sign_extend $end
$var wire 16 %" dIn [15:0] $end
$var wire 32 &" dOut [31:0] $end
$upscope $end
$upscope $end
$upscope $end
$enddefinitions $end
#0
$dumpvars
bx &"
bx %"
bx $"
b0 #"
x""
bx !"
b0 ~
x}
bx |
b0 {
xz
bx y
b0 x
xw
bx v
b0 u
xt
bx s
b0 r
xq
bx p
b0 o
xn
bx m
b0 l
xk
bx j
b0 i
xh
bx g
b0 f
xe
bx d
b0 c
xb
bx a
b0 `
x_
bx ^
b0 ]
x\
bx [
b0 Z
xY
bx X
b0 W
xV
bx U
b0 T
xS
bx R
bx Q
bx P
bx O
bx N
b0 M
bx L
bx K
bx J
bx I
bx H
bx G
bx F
bx E
bx D
bx C
bx B
bx A
bx @
bz ?
bx >
bx =
bx <
bz ;
bz :
b0 9
bx 8
bx 7
bz 6
bx 5
bx 4
bx 3
bz 2
b0 1
bx 0
bx /
bx .
bx -
bx ,
bx +
bx *
bx )
bx (
x'
1&
1%
bx $
0#
0"
bx !
$end
#10000
1#
1"
#20000
0"
#30000
b101 2
b101 6
b101 ?
b101 1
b101 9
b101 M
b101 T
b101 W
b101 Z
b101 ]
b101 `
b101 c
b101 f
b101 i
b101 l
b101 o
b101 r
b101 u
b101 x
b101 {
b101 ~
b101 #"
1S
0V
0Y
0\
0_
0b
0e
0h
0k
0n
0q
0t
0w
0z
0}
0""
b1 3
b1 <
b1 D
b11 4
b11 8
b11 C
b101 .
b101 =
b101 &"
b101 /
b101 F
b101 %"
b0 0
b0 E
b0 N
b0 *
b0 >
b0 Q
b101 (
b101 H
b101 R
b0 +
b0 7
b0 O
b0 )
b0 G
b0 P
b1000100 5
b1000100 K
b1011 @
b11 A
1'
b111011000000000000010100000000 !
b111011000000000000010100000000 $
b111011000000000000010100000000 -
b111011000000000000010100000000 B
b111011000000000000010100000000 J
b10000 I
0#
b0 $"
b0 !"
b0 |
b0 y
b0 v
b0 s
b0 p
b0 m
b0 j
b0 g
b0 d
b0 a
b0 ^
b0 [
b0 X
b0 U
b1000000 ,
b1000000 L
1"
#40000
0"
#50000
b0 3
b0 <
b0 D
b0 .
b0 =
b0 &"
b0 /
b0 F
b0 %"
b101 *
b101 >
b101 Q
b0 (
b0 H
b0 R
b1001000 5
b1001000 K
b1010 1
b1010 9
b1010 M
b1010 T
b1010 W
b1010 Z
b1010 ]
b1010 `
b1010 c
b1010 f
b1010 i
b1010 l
b1010 o
b1010 r
b1010 u
b1010 x
b1010 {
b1010 ~
b1010 #"
b1111 @
b111111000000000000000000000000 !
b111111000000000000000000000000 $
b111111000000000000000000000000 -
b111111000000000000000000000000 B
b111111000000000000000000000000 J
b10001 I
b1000100 ,
b1000100 L
b101 U
b101 +
b101 7
b101 O
1"
#60000
0"
#70000
b1 3
b1 <
b1 D
b110 .
b110 =
b110 &"
b110 /
b110 F
b110 %"
b110 (
b110 H
b110 R
b10000 1
b10000 9
b10000 M
b10000 T
b10000 W
b10000 Z
b10000 ]
b10000 `
b10000 c
b10000 f
b10000 i
b10000 l
b10000 o
b10000 r
b10000 u
b10000 x
b10000 {
b10000 ~
b10000 #"
b110 2
b110 6
b110 ?
b1001100 5
b1001100 K
b1011 @
b111011000000000000011000000000 !
b111011000000000000011000000000 $
b111011000000000000011000000000 -
b111011000000000000011000000000 B
b111011000000000000011000000000 J
b10010 I
b1010 U
b1010 +
b1010 7
b1010 O
b0 *
b0 >
b0 Q
b1001000 ,
b1001000 L
1"
#80000
0"
#90000
b10000 2
b10000 6
b10000 ?
b0 3
b0 <
b0 D
b0 .
b0 =
b0 &"
b0 /
b0 F
b0 %"
b10000 *
b10000 >
b10000 Q
b0 (
b0 H
b0 R
b1010000 5
b1010000 K
b100000 1
b100000 9
b100000 M
b100000 T
b100000 W
b100000 Z
b100000 ]
b100000 `
b100000 c
b100000 f
b100000 i
b100000 l
b100000 o
b100000 r
b100000 u
b100000 x
b100000 {
b100000 ~
b100000 #"
b1111 @
b111111000000000000000000000000 !
b111111000000000000000000000000 $
b111111000000000000000000000000 -
b111111000000000000000000000000 B
b111111000000000000000000000000 J
b10011 I
b1001100 ,
b1001100 L
b10000 U
b10000 +
b10000 7
b10000 O
1"
#100000
0"
#110000
b1 3
b1 <
b1 D
b101 .
b101 =
b101 &"
b101 /
b101 F
b101 %"
b101 (
b101 H
b101 R
b100101 1
b100101 9
b100101 M
b100101 T
b100101 W
b100101 Z
b100101 ]
b100101 `
b100101 c
b100101 f
b100101 i
b100101 l
b100101 o
b100101 r
b100101 u
b100101 x
b100101 {
b100101 ~
b100101 #"
b101 2
b101 6
b101 ?
b1010100 5
b1010100 K
b1011 @
b111011000000000000010100000000 !
b111011000000000000010100000000 $
b111011000000000000010100000000 -
b111011000000000000010100000000 B
b111011000000000000010100000000 J
b10100 I
b100000 U
b100000 +
b100000 7
b100000 O
b0 *
b0 >
b0 Q
b1010000 ,
b1010000 L
1"
#120000
0"
#130000
b1111 2
b1111 6
b1111 ?
b111 4
b111 8
b111 C
b1111 .
b1111 =
b1111 &"
b1111 /
b1111 F
b1111 %"
b1111 (
b1111 H
b1111 R
b1011000 5
b1011000 K
b101 1
b101 9
b101 M
b101 T
b101 W
b101 Z
b101 ]
b101 `
b101 c
b101 f
b101 i
b101 l
b101 o
b101 r
b101 u
b101 x
b101 {
b101 ~
b101 #"
b111 A
b1111011000000000000111100000000 !
b1111011000000000000111100000000 $
b1111011000000000000111100000000 -
b1111011000000000000111100000000 B
b1111011000000000000111100000000 J
b10101 I
b1010100 ,
b1010100 L
b100101 U
b100101 +
b100101 7
b100101 O
1"
#140000
0"
#150000
b101 1
b101 9
b101 M
b101 T
b101 W
b101 Z
b101 ]
b101 `
b101 c
b101 f
b101 i
b101 l
b101 o
b101 r
b101 u
b101 x
b101 {
b101 ~
b101 #"
b0 2
b0 6
b0 ?
b11 4
b11 8
b11 C
b0 .
b0 =
b0 &"
b0 /
b0 F
b0 %"
b101 *
b101 >
b101 Q
b0 (
b0 H
b0 R
b1011100 5
b1011100 K
b11 A
b111011000000000000000000000000 !
b111011000000000000000000000000 $
b111011000000000000000000000000 -
b111011000000000000000000000000 B
b111011000000000000000000000000 J
b10110 I
b101 U
b101 +
b101 7
b101 O
b1011000 ,
b1011000 L
1"
#160000
0"
#170000
b1 1
b1 9
b1 M
b1 T
b1 W
b1 Z
b1 ]
b1 `
b1 c
b1 f
b1 i
b1 l
b1 o
b1 r
b1 u
b1 x
b1 {
b1 ~
b1 #"
0S
1V
b0 3
b0 <
b0 D
b11111 4
b11111 8
b11111 C
b1 .
b1 =
b1 &"
b1 /
b1 F
b1 %"
b1 0
b1 E
b1 N
b0 *
b0 >
b0 Q
b1 (
b1 H
b1 R
b0 +
b0 7
b0 O
b1 )
b1 G
b1 P
b1100000 5
b1100000 K
b1110 @
b1111 A
b11111110000000000000000100010001 !
b11111110000000000000000100010001 $
b11111110000000000000000100010001 -
b11111110000000000000000100010001 B
b11111110000000000000000100010001 J
b10111 I
b1011100 ,
b1011100 L
1"
#180000
0"
#190000
b0 1
b0 9
b0 M
b0 T
b0 W
b0 Z
b0 ]
b0 `
b0 c
b0 f
b0 i
b0 l
b0 o
b0 r
b0 u
b0 x
b0 {
b0 ~
b0 #"
b10011 4
b10011 8
b10011 C
b1 2
b1 6
b1 ?
b1100100 5
b1100100 K
b11 A
b111110000000000000000100010001 !
b111110000000000000000100010001 $
b111110000000000000000100010001 -
b111110000000000000000100010001 B
b111110000000000000000100010001 J
b11000 I
b1 X
b1 +
b1 7
b1 O
b1 *
b1 >
b1 Q
b1100000 ,
b1100000 L
1"
#200000
0"
#210000
b1 1
b1 9
b1 M
b1 T
b1 W
b1 Z
b1 ]
b1 `
b1 c
b1 f
b1 i
b1 l
b1 o
b1 r
b1 u
b1 x
b1 {
b1 ~
b1 #"
0V
1Y
b11110 4
b11110 8
b11110 C
b10 0
b10 E
b10 N
b0 )
b0 G
b0 P
b1101000 5
b1101000 K
b0 2
b0 6
b0 ?
b1110 A
b11101110000000000000000100000010 !
b11101110000000000000000100000010 $
b11101110000000000000000100000010 -
b11101110000000000000000100000010 B
b11101110000000000000000100000010 J
b11001 I
b1100100 ,
b1100100 L
b0 X
b101 +
b101 7
b101 O
b0 *
b0 >
b0 Q
1"
#220000
0"
#230000
b11 2
b11 6
b11 ?
b11 1
b11 9
b11 M
b11 T
b11 W
b11 Z
b11 ]
b11 `
b11 c
b11 f
b11 i
b11 l
b11 o
b11 r
b11 u
b11 x
b11 {
b11 ~
b11 #"
1V
0Y
b1 3
b1 <
b1 D
b11 4
b11 8
b11 C
b11 .
b11 =
b11 &"
b11 /
b11 F
b11 %"
b1 0
b1 E
b1 N
b11 (
b11 H
b11 R
b0 +
b0 7
b0 O
b100 )
b100 G
b100 P
b1101100 5
b1101100 K
b1011 @
b11 A
b111011000000000000001101000001 !
b111011000000000000001101000001 $
b111011000000000000001101000001 -
b111011000000000000001101000001 B
b111011000000000000001101000001 J
b11010 I
b1 [
b1101000 ,
b1101000 L
1"
#240000
0"
#250000
b101 2
b101 6
b101 ?
b11111111111111111111111111111110 1
b11111111111111111111111111111110 9
b11111111111111111111111111111110 M
b11111111111111111111111111111110 T
b11111111111111111111111111111110 W
b11111111111111111111111111111110 Z
b11111111111111111111111111111110 ]
b11111111111111111111111111111110 `
b11111111111111111111111111111110 c
b11111111111111111111111111111110 f
b11111111111111111111111111111110 i
b11111111111111111111111111111110 l
b11111111111111111111111111111110 o
b11111111111111111111111111111110 r
b11111111111111111111111111111110 u
b11111111111111111111111111111110 x
b11111111111111111111111111111110 {
b11111111111111111111111111111110 ~
b11111111111111111111111111111110 #"
0V
1Y
b0 3
b0 <
b0 D
b10 4
b10 8
b10 C
b0 .
b0 =
b0 &"
b0 /
b0 F
b0 %"
b10 0
b10 E
b10 N
b101 *
b101 >
b101 Q
b0 (
b0 H
b0 R
b11 +
b11 7
b11 O
b1 )
b1 G
b1 P
b1110000 5
b1110000 K
b1111 @
b10 A
b101111000000000000000000010010 !
b101111000000000000000000010010 $
b101111000000000000000000010010 -
b101111000000000000000000010010 B
b101111000000000000000000010010 J
b11011 I
b1101100 ,
b1101100 L
b11 X
1"
#260000
0"
#270000
b11111111111111111111111111111100 2
b11111111111111111111111111111100 6
b11111111111111111111111111111100 ?
b11111111111111111111111111111010 1
b11111111111111111111111111111010 9
b11111111111111111111111111111010 M
b11111111111111111111111111111010 T
b11111111111111111111111111111010 W
b11111111111111111111111111111010 Z
b11111111111111111111111111111010 ]
b11111111111111111111111111111010 `
b11111111111111111111111111111010 c
b11111111111111111111111111111010 f
b11111111111111111111111111111010 i
b11111111111111111111111111111010 l
b11111111111111111111111111111010 o
b11111111111111111111111111111010 r
b11111111111111111111111111111010 u
b11111111111111111111111111111010 x
b11111111111111111111111111111010 {
b11111111111111111111111111111010 ~
b11111111111111111111111111111010 #"
b1 3
b1 <
b1 D
b11 4
b11 8
b11 C
b11111111111111111111111111111100 .
b11111111111111111111111111111100 =
b11111111111111111111111111111100 &"
b1111111111111100 /
b1111111111111100 F
b1111111111111100 %"
b0 *
b0 >
b0 Q
b1100 (
b1100 H
b1100 R
b11111111111111111111111111111110 +
b11111111111111111111111111111110 7
b11111111111111111111111111111110 O
b10 )
b10 G
b10 P
b1110100 5
b1110100 K
b1011 @
b11 A
b111011111111111111110000100010 !
b111011111111111111110000100010 $
b111011111111111111110000100010 -
b111011111111111111110000100010 B
b111011111111111111110000100010 J
b11100 I
b11111111111111111111111111111110 [
b1110000 ,
b1110000 L
1"
#280000
0"
#290000
bz 2
bz 6
bz ?
0Y
1z
bz 3
bz <
bz D
bz 4
bz 8
bz C
b11011110 .
b11011110 =
b11011110 &"
b11011110 /
b11011110 F
b11011110 %"
b1101 0
b1101 E
b1101 N
b1110 (
b1110 H
b1110 R
b1010 )
b1010 G
b1010 P
b1110100 5
b1110100 K
b0 1
b0 9
b0 M
b0 T
b0 W
b0 Z
b0 ]
b0 `
b0 c
b0 f
b0 i
b0 l
b0 o
b0 r
b0 u
b0 x
b0 {
b0 ~
b0 #"
b0 @
b0 A
b1101111010101101 !
b1101111010101101 $
b1101111010101101 -
b1101111010101101 B
b1101111010101101 J
b11101 I
b1110100 ,
b1110100 L
b11111111111111111111111111111010 [
b0 +
b0 7
b0 O
1"
