verilog/Mux4to1.v
module Mux4to1(
input clk, reset,
input [1:0] select,
input [BIT_WIDTH-1:0] in0, in1, in2, in3,
output reg [BIT_WIDTH-1:0] out
);

parameter BIT_WIDTH = 32;

always @(*) begin
    case (select)
        0: out <= in0;
        1: out <= in1;
        2: out <= in2;
        3: out <= in3;
        default: out <= {BIT_WIDTH{1'bz}};
    endcase
end

endmodule

verilog/Memory.v
module Memory (
input clk, reset, en_write,
input [ADDR_BIT_WIDTH - 1 : 0] addr,
input [DATA_BIT_WIDTH - 1 : 0] data_in,
output [DATA_BIT_WIDTH - 1 : 0] data_out
);

parameter MEM_INIT_FILE = "";
parameter ADDR_BIT_WIDTH = 11;
parameter DATA_BIT_WIDTH = 32;

localparam SIZE = (1 << ADDR_BIT_WIDTH);

(* ram_init_file = MEM_INIT_FILE *)

reg[DATA_BIT_WIDTH - 1 : 0] data[0 : SIZE - 1];

assign data_out = data[addr];

always @(posedge clk) begin
    if (en_write)
        data[addr] <= data_in;
end

endmodule

verilog/Processor.vh
`ifndef _DECODER_VH_
`define _DECODER_VH_

`define OP_ALUR     4'b1111
`define OP_ALUI     4'b1011
`define OP_CMPR     4'b1110
`define OP_CMPI     4'b1010
`define OP_BCOND    4'b0000
`define OP_SW       4'b1000
`define OP_LW       4'b1001
`define OP_JAL      4'b0001

`define FN_ADD      5'b00011
`define FN_SUB      5'b00010
`define FN_AND      5'b00111
`define FN_OR       5'b00110
`define FN_XOR      5'b00101
`define FN_NAND     5'b01011
`define FN_NOR      5'b01010
`define FN_XNOR     5'b01001

`define FN_F        5'b10011
`define FN_EQ       5'b11100
`define FN_LT       5'b11101
`define FN_LTE      5'b10010
`define FN_T        5'b11111
`define FN_NE       5'b10000
`define FN_GTE      5'b10001
`define FN_GT       5'b11110

`define ALU_SRC2_REG2   2'b00
`define ALU_SRC2_IMM    2'b01
`define ALU_SRC2_IMM4   2'b10
`define ALU_SRC2_ZERO   2'b11

`define REG_IN_PC4      2'b00
`define REG_IN_DOUT     2'b01
`define REG_IN_ALU      2'b10

`define PC_IN_IMM4      2'b00
`define PC_IN_ALU       2'b01
`define PC_IN_PC4       2'b10
`define PC_IN_PC        2'b11

`define DEAD            16'hDEAD

`endif

verilog/Alu.v
`include "Processor.vh"

module Alu(
input [4:0] alu_fn,
input [BIT_WIDTH-1:0] in1, in2,
output reg [BIT_WIDTH-1:0] out
);

parameter BIT_WIDTH = 32;

always @(*) begin
    case (alu_fn)
        `FN_ADD  : out = in1 + in2;
        `FN_SUB  : out = in1 - in2;
        `FN_AND  : out = in1 & in2;
        `FN_OR   : out = in1 | in2;
        `FN_XOR  : out = in1 ^ in2;
        `FN_NAND : out = in1 ~& in2;
        `FN_NOR  : out = in1 ~| in2;
        `FN_XNOR : out = in1 ~^ in2;

        `FN_F    : out = 0;
        `FN_EQ   : out = (in1 == in2) ? 1 : 0;
        `FN_LT   : out = (in1 < in2) ? 1 : 0;
        `FN_LTE  : out = (in1 <= in2) ? 1 : 0;
        `FN_T    : out = 1;
        `FN_NE   : out = (in1 != in2) ? 1 : 0;
        `FN_GTE  : out = (in1 >= in2) ? 1 : 0;
        `FN_GT   : out = (in1 > in2) ? 1 : 0;
        default : out = 0;
    endcase
end

endmodule

verilog/SignExtension.v
module SignExtension(dIn, dOut);
  parameter IN_BIT_WIDTH = 16;
  parameter OUT_BIT_WIDTH = 32;

  input [(IN_BIT_WIDTH-1):0]  dIn;
  output[(OUT_BIT_WIDTH-1):0] dOut;

  assign dOut = {{(OUT_BIT_WIDTH - IN_BIT_WIDTH){dIn[IN_BIT_WIDTH-1]}}, dIn};
endmodule

verilog/Register.v
module Register(
input clk, reset, en_write,
input[BIT_WIDTH - 1: 0] data_in,
output reg [BIT_WIDTH - 1: 0] data_out
);

parameter BIT_WIDTH = 32;
parameter RESET_VALUE = 0;

always @(posedge clk) begin
    if (reset == 1'b1)
        data_out <= RESET_VALUE;
    else if (en_write == 1'b1)
        data_out <= data_in;
end

endmodule

verilog/RegisterFile.v
`include "Register.v"

module RegisterFile(
input clk, reset, en_write,
input [REG_INDEX_WIDTH-1:0] sr1_ind, sr2_ind, dr_ind,
input [BIT_WIDTH-1:0] data_in,
output [BIT_WIDTH-1:0] sr1, sr2
);

parameter BIT_WIDTH = 32;
parameter REG_INDEX_WIDTH = 4;
parameter RESET_VALUE = 0;

wire [BIT_WIDTH-1:0] reg_data_out [(1<<REG_INDEX_WIDTH)-1:0];

genvar i;
generate
    for (i=0; i<(1<<REG_INDEX_WIDTH); i=i+1) begin
        wire en_write1;
        Register #(
            .BIT_WIDTH(BIT_WIDTH), .RESET_VALUE(RESET_VALUE)
            ) regs (
            .clk (clk),
            .reset (reset),
            .en_write (en_write1),
            .data_in (data_in),
            .data_out (reg_data_out[i])
            );
        assign en_write1 = (dr_ind == i) ? en_write : 0;
    end
endgenerate


assign sr1 = reg_data_out[sr1_ind];
assign sr2 = reg_data_out[sr2_ind];

endmodule

verilog/Decoder.v
`include "Processor.vh"

module Decoder(
input [INST_BIT_WIDTH-1:0] data,
input [DATA_BIT_WIDTH-1:0] alu_out,
output reg [4:0] alu_fn,
output reg [REG_INDEX_WIDTH-1:0] src_reg1, src_reg2, dest_reg,
output reg [IMM_BIT_WIDTH-1:0] imm,
output reg [1:0] sel_alu_sr2, sel_pc, sel_reg_din,
output reg wr_reg, wr_mem
);

localparam REG_INDEX_WIDTH = 4;
localparam DATA_BIT_WIDTH = 32;
localparam INST_BIT_WIDTH = 32;
localparam IMM_BIT_WIDTH = 16;

wire [3:0] fn, b_fn;
wire [3:0] opcode;

assign fn = data[31:28];
assign opcode = data[27:24];

always @(*) begin
    src_reg1 = data[7:4];
    src_reg2 = data[11:8];
    dest_reg = data[3:0];
    imm = data[23:8];
    if (opcode == `OP_SW || opcode == `OP_BCOND) begin
        src_reg1 = data[3:0];
        src_reg2 = data[7:4];
    end
end

always @(*) begin
    alu_fn      = 4'bzzzz;;
    wr_mem      = 1'b0;
    wr_reg      = 1'b0;
    sel_pc      = `PC_IN_PC;
    sel_reg_din = 2'bzz;
    sel_alu_sr2 = 2'bzz;
    if (data[15:0] != `DEAD) begin
        case (opcode)
            `OP_ALUR: begin
                alu_fn      = {1'b0, fn};
                sel_alu_sr2 = `ALU_SRC2_REG2;
                sel_pc      = `PC_IN_PC4;
                wr_reg      = 1'b1;
                sel_reg_din = `REG_IN_ALU;
            end
            `OP_ALUI: begin
                alu_fn      = {1'b0, fn};
                sel_alu_sr2 = `ALU_SRC2_IMM;
                sel_pc      = `PC_IN_PC4;
                wr_reg      = 1'b1;
                sel_reg_din = `REG_IN_ALU;
            end
            `OP_CMPR: begin
                alu_fn      = {1'b1, fn};
                sel_alu_sr2 = `ALU_SRC2_REG2;
                sel_pc      = `PC_IN_PC4;
                wr_reg      = 1'b1;
                sel_reg_din = `REG_IN_ALU;
            end
            `OP_CMPI: begin
                alu_fn      = {1'b1, fn};
                sel_alu_sr2 = `ALU_SRC2_IMM;
                sel_pc      = `PC_IN_PC4;
                wr_reg      = 1'b1;
                sel_reg_din = `REG_IN_ALU;
            end
            `OP_BCOND: begin
                sel_alu_sr2 = `ALU_SRC2_REG2;
                alu_fn = {1'b1, fn};
                if (fn[3:2] == 2'b01) begin
                    alu_fn  = {1'b1, 2'b00, fn[1:0]};
                    sel_alu_sr2 = `ALU_SRC2_ZERO;
                end else if (fn[3:2] == 2'b10) begin
                    alu_fn  = {1'b1, 2'b11, fn[1:0]};
                    sel_alu_sr2 = `ALU_SRC2_ZERO;
                end

                if (alu_out == 32'b1)
                    sel_pc  = `PC_IN_IMM4;
                else
                    sel_pc  = `PC_IN_PC4;
            end
            `OP_SW: begin
                alu_fn      = {1'b0, `FN_ADD};
                sel_alu_sr2 = `ALU_SRC2_IMM;
                sel_pc      = `PC_IN_PC4;
                wr_mem      = 1'b1;
            end
            `OP_LW: begin
                alu_fn      = {1'b0, `FN_ADD};
                sel_alu_sr2 = `ALU_SRC2_IMM;
                sel_pc      = `PC_IN_PC4;
                wr_reg      = 1'b1;
                sel_reg_din = `REG_IN_ALU;
            end
            `OP_JAL: begin
                alu_fn      = {1'b0, `FN_ADD};
                sel_alu_sr2 = `ALU_SRC2_IMM4;
                sel_reg_din = `REG_IN_PC4;
                if (alu_out == 32'b1)
                    sel_pc  = `PC_IN_ALU;
                else
                    sel_pc  = `PC_IN_PC4;
            end
        endcase
    end
end

endmodule

verilog/InstMemory.v
module InstMemory(
input[ADDR_BIT_WIDTH - 1: 0] addr,
output[DATA_BIT_WIDTH - 1: 0] dataOut
);

parameter MEM_INIT_FILE = "";
parameter ADDR_BIT_WIDTH = 11;
parameter DATA_BIT_WIDTH = 32;
parameter N_WORDS = (1 << ADDR_BIT_WIDTH);

(* ram_init_file = MEM_INIT_FILE *)

reg [15:0] test1;
reg[DATA_BIT_WIDTH - 1: 0] data[0: N_WORDS - 1];

assign dataOut = data[addr];

endmodule

verilog/Processor.v
`include "Alu.v"
`include "Decoder.v"
`include "InstMemory.v"
`include "Mux4to1.v"
`include "Register.v"
`include "RegisterFile.v"
`include "SignExtension.v"
`include "Memory.v"

module Processor (
input clk,
input reset,
output [INST_BIT_WIDTH - 1: 0] inst_word_out // For testing
);

parameter DBITS                 = 32;
parameter IMEM_INIT_FILE        = "Sorter2.mif";
parameter DMEM_INIT_FILE        = "";

parameter DMEM_ADDR_BIT_WIDTH   = 11;
parameter IMEM_ADDR_BIT_WIDTH   = 11;

localparam INST_SIZE            = 32'd4;
localparam INST_BIT_WIDTH       = 32;
localparam START_PC             = 32'h40;
localparam REG_INDEX_BIT_WIDTH  = 4;
localparam IMEM_WORD_BITS       = 2;
localparam DMEM_WORD_BITS       = 2;


wire [DBITS-1:0] alu_out;
reg [DBITS-1:0] alu_in2;

// PC Mux
always @(*) begin
    case (sel_pc)
        `PC_IN_IMM4:    pc_in = imm_ext4 + pc_out + 4;
        `PC_IN_ALU:     pc_in = alu_out;
        `PC_IN_PC4:     pc_in = pc_out + 4;
        `PC_IN_PC:      pc_in = pc_out;
        default:        pc_in = {DBITS{1'bz}};
    endcase
end

// PC signals
reg [DBITS - 1: 0] pc_in;
wire [DBITS - 1: 0] pc_out;
wire pc_en = 1'b1;
Register #(
    .BIT_WIDTH(DBITS), .RESET_VALUE(START_PC)
    ) pc (
    clk, reset, pc_en, pc_in, pc_out
);


// Instruction memory signals
wire [INST_BIT_WIDTH - 1: 0] inst_word;
assign inst_word_out = inst_word;
InstMemory #(
    IMEM_INIT_FILE,
    IMEM_ADDR_BIT_WIDTH,
    INST_BIT_WIDTH
    ) instMem (
    .addr (pc_out[IMEM_ADDR_BIT_WIDTH + IMEM_WORD_BITS - 1: IMEM_WORD_BITS]),
    .dataOut (inst_word)
);


// Control/data signals from decoder
wire [4:0] alu_fn;
wire [3:0] src_reg1, src_reg2, dest_reg;
wire [15:0] imm;
wire [1:0] sel_pc, sel_alu_sr2, sel_reg_din;
wire wr_reg, wr_mem;
Decoder decoder (
    .data (inst_word),
    .alu_out (alu_out),
    .alu_fn (alu_fn),
    .src_reg1 (src_reg1),
    .src_reg2 (src_reg2),
    .dest_reg (dest_reg),
    .imm (imm),
    .sel_alu_sr2 (sel_alu_sr2),
    .sel_pc (sel_pc),
    .sel_reg_din (sel_reg_din),
    .wr_reg (wr_reg),
    .wr_mem (wr_mem)
);

// Register File Mux
always @(*) begin
    case (sel_reg_din)
        `REG_IN_PC4:    regs_din = pc_out + 4;
        `REG_IN_DOUT:   regs_din = data_out;
        `REG_IN_ALU:    regs_din = alu_out;
        default:        regs_din = {DBITS{1'bz}};
    endcase
end

reg [DBITS-1:0] regs_din;
wire [DBITS-1:0] regs_out1, regs_out2;
RegisterFile #(
    .BIT_WIDTH (DBITS),
    .REG_INDEX_WIDTH (REG_INDEX_BIT_WIDTH),
    .RESET_VALUE (0)
    ) regs (
    .clk (clk),
    .reset (reset),
    .en_write (wr_reg),
    .sr1_ind (src_reg1),
    .sr2_ind (src_reg2),
    .dr_ind (dest_reg),
    .data_in (regs_din),
    .sr1 (regs_out1),
    .sr2 (regs_out2)
);


// Sign extended signals
wire [DBITS-1:0] imm_ext;
wire [DBITS-1:0] imm_ext4 = {imm_ext[DBITS-3:0], 2'b00};
SignExtension #(
    .IN_BIT_WIDTH (16),
    .OUT_BIT_WIDTH (DBITS)
    ) sign_extend (
    .dIn (imm),
    .dOut (imm_ext)
);


// ALU input 2 Mux
always @(*) begin
    case (sel_alu_sr2)
        `ALU_SRC2_REG2:     alu_in2 = regs_out2;
        `ALU_SRC2_IMM:      alu_in2 = imm_ext;
        `ALU_SRC2_IMM4:     alu_in2 = imm_ext4;
        `ALU_SRC2_ZERO:     alu_in2 = 0;
        default:            alu_in2 = {DBITS{1'bz}};
    endcase
end

// ALU signals
Alu #(
    .BIT_WIDTH (DBITS)
    ) alu (
    .alu_fn (alu_fn),
    .in1 (regs_out1),
    .in2 (alu_in2),
    .out (alu_out)
);



wire [DBITS-1:0] data_out;
Memory #(
    .MEM_INIT_FILE (DMEM_INIT_FILE),
    .ADDR_BIT_WIDTH (DMEM_ADDR_BIT_WIDTH),
    .DATA_BIT_WIDTH (DBITS)
    ) data_memory (
    .clk (clk),
    .reset (reset),
    .en_write (wr_mem),
    .addr (alu_out[DMEM_ADDR_BIT_WIDTH + DMEM_WORD_BITS - 1: DMEM_WORD_BITS]),
    .data_in (regs_out2),
    .data_out (data_out)
);


endmodule

verilog/testbenches/Processor_tb.v
`timescale 1ns/1ps

`include "Processor.v"

module Processor_tb;

parameter DBITS = 32;

reg clk, reset;
wire [DBITS-1:0] instr_word;

Processor #(
    .DBITS (DBITS),
    .IMEM_INIT_FILE ("test.mif")
    ) processor (
    .clk (clk),
    .reset (reset),
    .inst_word_out (instr_word)
);

initial begin
    $readmemh("../../assembly-files/test.hex", processor.instMem.data);
    $dumpfile("Processor.vcd");
    $dumpvars(0, Processor_tb);
end

initial begin
    reset <= 0;
    clk <= 0;
    @(posedge clk);
    reset <= 1;
    @(posedge clk);
    reset <= 0;
    @(posedge clk);

    @(instr_word == 32'h0000DEAD);
    @(posedge clk);
    @(posedge clk);
    $finish;

    // @(posedge clk);
    // @(posedge clk);
    // @(posedge clk);
    // @(posedge clk);
    // @(posedge clk);
    // @(posedge clk);
    // @(posedge clk);
    // @(posedge clk);
    // @(posedge clk);
    // @(posedge clk);
    // @(posedge clk);
    // @(posedge clk);
    // @(posedge clk);
    // @(posedge clk);
    // @(posedge clk);
    // @(posedge clk);

    $finish;
end

always #10 clk = ~clk;

endmodule

verilog/testbenches/Processor.vcd
$date
	Sun Nov 12 01:47:37 2017
$end
$version
	Icarus Verilog
$end
$timescale
	1ps
$end
$scope module Processor_tb $end
$var wire 32 ! instr_word [31:0] $end
$var reg 1 " clk $end
$var reg 1 # reset $end
$scope module processor $end
$var wire 1 " clk $end
$var wire 32 $ inst_word_out [31:0] $end
$var wire 1 % pc_en $end
$var wire 1 # reset $end
$var wire 1 & wr_reg $end
$var wire 1 ' wr_mem $end
$var wire 4 ( src_reg2 [3:0] $end
$var wire 4 ) src_reg1 [3:0] $end
$var wire 2 * sel_reg_din [1:0] $end
$var wire 2 + sel_pc [1:0] $end
$var wire 2 , sel_alu_sr2 [1:0] $end
$var wire 32 - regs_out2 [31:0] $end
$var wire 32 . regs_out1 [31:0] $end
$var wire 32 / pc_out [31:0] $end
$var wire 32 0 inst_word [31:0] $end
$var wire 32 1 imm_ext4 [31:0] $end
$var wire 32 2 imm_ext [31:0] $end
$var wire 16 3 imm [15:0] $end
$var wire 4 4 dest_reg [3:0] $end
$var wire 32 5 data_out [31:0] $end
$var wire 32 6 alu_out [31:0] $end
$var wire 5 7 alu_fn [4:0] $end
$var reg 32 8 alu_in2 [31:0] $end
$var reg 32 9 pc_in [31:0] $end
$var reg 32 : regs_din [31:0] $end
$scope module alu $end
$var wire 32 ; in2 [31:0] $end
$var wire 32 < in1 [31:0] $end
$var wire 5 = alu_fn [4:0] $end
$var reg 32 > out [31:0] $end
$upscope $end
$scope module data_memory $end
$var wire 11 ? addr [10:0] $end
$var wire 1 " clk $end
$var wire 32 @ data_out [31:0] $end
$var wire 1 # reset $end
$var wire 1 ' en_write $end
$var wire 32 A data_in [31:0] $end
$upscope $end
$scope module decoder $end
$var wire 32 B alu_out [31:0] $end
$var wire 4 C opcode [3:0] $end
$var wire 4 D fn [3:0] $end
$var wire 32 E data [31:0] $end
$var reg 5 F alu_fn [4:0] $end
$var reg 4 G dest_reg [3:0] $end
$var reg 16 H imm [15:0] $end
$var reg 2 I sel_alu_sr2 [1:0] $end
$var reg 2 J sel_pc [1:0] $end
$var reg 2 K sel_reg_din [1:0] $end
$var reg 4 L src_reg1 [3:0] $end
$var reg 4 M src_reg2 [3:0] $end
$var reg 1 ' wr_mem $end
$var reg 1 & wr_reg $end
$upscope $end
$scope module instMem $end
$var wire 11 N addr [10:0] $end
$var wire 32 O dataOut [31:0] $end
$upscope $end
$scope module pc $end
$var wire 1 " clk $end
$var wire 32 P data_in [31:0] $end
$var wire 1 % en_write $end
$var wire 1 # reset $end
$var reg 32 Q data_out [31:0] $end
$upscope $end
$scope module regs $end
$var wire 1 " clk $end
$var wire 32 R data_in [31:0] $end
$var wire 4 S dr_ind [3:0] $end
$var wire 1 & en_write $end
$var wire 1 # reset $end
$var wire 32 T sr1 [31:0] $end
$var wire 4 U sr1_ind [3:0] $end
$var wire 32 V sr2 [31:0] $end
$var wire 4 W sr2_ind [3:0] $end
$scope begin genblk1[0] $end
$var wire 1 X en_write1 $end
$scope module regs $end
$var wire 1 " clk $end
$var wire 32 Y data_in [31:0] $end
$var wire 1 X en_write $end
$var wire 1 # reset $end
$var reg 32 Z data_out [31:0] $end
$upscope $end
$upscope $end
$scope begin genblk1[1] $end
$var wire 1 [ en_write1 $end
$scope module regs $end
$var wire 1 " clk $end
$var wire 32 \ data_in [31:0] $end
$var wire 1 [ en_write $end
$var wire 1 # reset $end
$var reg 32 ] data_out [31:0] $end
$upscope $end
$upscope $end
$scope begin genblk1[2] $end
$var wire 1 ^ en_write1 $end
$scope module regs $end
$var wire 1 " clk $end
$var wire 32 _ data_in [31:0] $end
$var wire 1 ^ en_write $end
$var wire 1 # reset $end
$var reg 32 ` data_out [31:0] $end
$upscope $end
$upscope $end
$scope begin genblk1[3] $end
$var wire 1 a en_write1 $end
$scope module regs $end
$var wire 1 " clk $end
$var wire 32 b data_in [31:0] $end
$var wire 1 a en_write $end
$var wire 1 # reset $end
$var reg 32 c data_out [31:0] $end
$upscope $end
$upscope $end
$scope begin genblk1[4] $end
$var wire 1 d en_write1 $end
$scope module regs $end
$var wire 1 " clk $end
$var wire 32 e data_in [31:0] $end
$var wire 1 d en_write $end
$var wire 1 # reset $end
$var reg 32 f data_out [31:0] $end
$upscope $end
$upscope $end
$scope begin genblk1[5] $end
$var wire 1 g en_write1 $end
$scope module regs $end
$var wire 1 " clk $end
$var wire 32 h data_in [31:0] $end
$var wire 1 g en_write $end
$var wire 1 # reset $end
$var reg 32 i data_out [31:0] $end
$upscope $end
$upscope $end
$scope begin genblk1[6] $end
$var wire 1 j en_write1 $end
$scope module regs $end
$var wire 1 " clk $end
$var wire 32 k data_in [31:0] $end
$var wire 1 j en_write $end
$var wire 1 # reset $end
$var reg 32 l data_out [31:0] $end
$upscope $end
$upscope $end
$scope begin genblk1[7] $end
$var wire 1 m en_write1 $end
$scope module regs $end
$var wire 1 " clk $end
$var wire 32 n data_in [31:0] $end
$var wire 1 m en_write $end
$var wire 1 # reset $end
$var reg 32 o data_out [31:0] $end
$upscope $end
$upscope $end
$scope begin genblk1[8] $end
$var wire 1 p en_write1 $end
$scope module regs $end
$var wire 1 " clk $end
$var wire 32 q data_in [31:0] $end
$var wire 1 p en_write $end
$var wire 1 # reset $end
$var reg 32 r data_out [31:0] $end
$upscope $end
$upscope $end
$scope begin genblk1[9] $end
$var wire 1 s en_write1 $end
$scope module regs $end
$var wire 1 " clk $end
$var wire 32 t data_in [31:0] $end
$var wire 1 s en_write $end
$var wire 1 # reset $end
$var reg 32 u data_out [31:0] $end
$upscope $end
$upscope $end
$scope begin genblk1[10] $end
$var wire 1 v en_write1 $end
$scope module regs $end
$var wire 1 " clk $end
$var wire 32 w data_in [31:0] $end
$var wire 1 v en_write $end
$var wire 1 # reset $end
$var reg 32 x data_out [31:0] $end
$upscope $end
$upscope $end
$scope begin genblk1[11] $end
$var wire 1 y en_write1 $end
$scope module regs $end
$var wire 1 " clk $end
$var wire 32 z data_in [31:0] $end
$var wire 1 y en_write $end
$var wire 1 # reset $end
$var reg 32 { data_out [31:0] $end
$upscope $end
$upscope $end
$scope begin genblk1[12] $end
$var wire 1 | en_write1 $end
$scope module regs $end
$var wire 1 " clk $end
$var wire 32 } data_in [31:0] $end
$var wire 1 | en_write $end
$var wire 1 # reset $end
$var reg 32 ~ data_out [31:0] $end
$upscope $end
$upscope $end
$scope begin genblk1[13] $end
$var wire 1 !" en_write1 $end
$scope module regs $end
$var wire 1 " clk $end
$var wire 32 "" data_in [31:0] $end
$var wire 1 !" en_write $end
$var wire 1 # reset $end
$var reg 32 #" data_out [31:0] $end
$upscope $end
$upscope $end
$scope begin genblk1[14] $end
$var wire 1 $" en_write1 $end
$scope module regs $end
$var wire 1 " clk $end
$var wire 32 %" data_in [31:0] $end
$var wire 1 $" en_write $end
$var wire 1 # reset $end
$var reg 32 &" data_out [31:0] $end
$upscope $end
$upscope $end
$scope begin genblk1[15] $end
$var wire 1 '" en_write1 $end
$scope module regs $end
$var wire 1 " clk $end
$var wire 32 (" data_in [31:0] $end
$var wire 1 '" en_write $end
$var wire 1 # reset $end
$var reg 32 )" data_out [31:0] $end
$upscope $end
$upscope $end
$upscope $end
$scope module sign_extend $end
$var wire 16 *" dIn [15:0] $end
$var wire 32 +" dOut [31:0] $end
$upscope $end
$upscope $end
$upscope $end
$enddefinitions $end
#0
$dumpvars
bx +"
bx *"
bx )"
bz ("
0'"
bx &"
bz %"
0$"
bx #"
bz ""
0!"
bx ~
bz }
0|
bx {
bz z
0y
bx x
bz w
0v
bx u
bz t
0s
bx r
bz q
0p
bx o
bz n
0m
bx l
bz k
0j
bx i
bz h
0g
bx f
bz e
0d
bx c
bz b
0a
bx `
bz _
0^
bx ]
bz \
0[
bx Z
bz Y
0X
bx W
bx V
bx U
bx T
bx S
bz R
bx Q
bx P
bx O
bx N
bx M
bx L
bz K
b11 J
bz I
bx H
bx G
b0zzzz F
bx E
bx D
bx C
b0 B
bx A
bx @
b0 ?
b0 >
b0zzzz =
bx <
bz ;
bz :
bx 9
bz 8
b0zzzz 7
b0 6
bx 5
bx 4
bx 3
bx 2
bx00 1
bx 0
bx /
bx .
bx -
bz ,
b11 +
bz *
bx )
bx (
0'
0&
1%
bx $
0#
0"
bx !
$end
#10000
1#
1"
#20000
0"
#30000
b10 ?
b1010 :
b1010 R
b1010 Y
b1010 \
b1010 _
b1010 b
b1010 e
b1010 h
b1010 k
b1010 n
b1010 q
b1010 t
b1010 w
b1010 z
b1010 }
b1010 ""
b1010 %"
b1010 ("
1[
b1010 6
b1010 >
b1010 B
b1010 8
b1010 ;
b10 *
b10 K
1&
b10 +
b10 J
b1 ,
b1 I
b11 7
b11 =
b11 F
b101000 1
b1011 C
b11 D
b1010 2
b1010 +"
b1010 3
b1010 H
b1010 *"
b1 4
b1 G
b1 S
b0 -
b0 A
b0 V
b1010 (
b1010 M
b1010 W
b0 .
b0 <
b0 T
b1 )
b1 L
b1 U
b111011000000000000101000010001 !
b111011000000000000101000010001 $
b111011000000000000101000010001 0
b111011000000000000101000010001 E
b111011000000000000101000010001 O
b10000 N
b1000100 9
b1000100 P
0#
b0 )"
b0 &"
b0 #"
b0 ~
b0 {
b0 x
b0 u
b0 r
b0 o
b0 l
b0 i
b0 f
b0 c
b0 `
b0 ]
b0 Z
b1000000 /
b1000000 Q
1"
#40000
0"
#50000
b1000 1
1X
b10 8
b10 ;
0[
b10 2
b10 +"
b10 3
b10 H
b10 *"
b0 4
b0 G
b0 S
b10 (
b10 M
b10 W
b0 )
b0 L
b0 U
b1 ,
b1 I
b10 *
b10 K
b10 +
b10 J
1&
b11 7
b11 =
b11 F
b0 ?
b111011000000000000001000000000 !
b111011000000000000001000000000 $
b111011000000000000001000000000 0
b111011000000000000001000000000 E
b111011000000000000001000000000 O
b10001 N
b1001000 9
b1001000 P
b10 :
b10 R
b10 Y
b10 \
b10 _
b10 b
b10 e
b10 h
b10 k
b10 n
b10 q
b10 t
b10 w
b10 z
b10 }
b10 ""
b10 %"
b10 ("
b10 6
b10 >
b10 B
b1000100 /
b1000100 Q
b1010 ]
b0 .
b0 <
b0 T
1"
#60000
0"
#70000
0X
b1010 -
b1010 A
b1010 V
b11111111111111111111111111111000 1
b1010 8
b1010 ;
b0 ?
bz :
bz R
bz Y
bz \
bz _
bz b
bz e
bz h
bz k
bz n
bz q
bz t
bz w
bz z
bz }
bz ""
bz %"
bz ("
b0 C
b1101 D
b0 ,
b0 I
bz *
bz K
b0 +
b0 J
0&
b11101 7
b11101 =
b11101 F
b11111111111111111111111111111110 2
b11111111111111111111111111111110 +"
b1111111111111110 3
b1111111111111110 H
b1111111111111110 *"
b1 (
b1 M
b1 W
b0 )
b0 L
b0 U
b1 6
b1 >
b1 B
b11010000111111111111111000010000 !
b11010000111111111111111000010000 $
b11010000111111111111111000010000 0
b11010000111111111111111000010000 E
b11010000111111111111111000010000 O
b10010 N
b1000100 9
b1000100 P
b10 Z
b10 .
b10 <
b10 T
b1001000 /
b1001000 Q
1"
#80000
0"
#90000
b1 ?
1X
b100 :
b100 R
b100 Y
b100 \
b100 _
b100 b
b100 e
b100 h
b100 k
b100 n
b100 q
b100 t
b100 w
b100 z
b100 }
b100 ""
b100 %"
b100 ("
b10 *
b10 K
1&
b100 6
b100 >
b100 B
b1000 1
b10 8
b10 ;
b1011 C
b11 D
b1 ,
b1 I
b10 +
b10 J
b11 7
b11 =
b11 F
b10 2
b10 +"
b10 3
b10 H
b10 *"
b0 -
b0 A
b0 V
b10 (
b10 M
b10 W
b111011000000000000001000000000 !
b111011000000000000001000000000 $
b111011000000000000001000000000 0
b111011000000000000001000000000 E
b111011000000000000001000000000 O
b10001 N
b1001000 9
b1001000 P
b1000100 /
b1000100 Q
1"
#100000
0"
#110000
0X
b0 ?
b1010 -
b1010 A
b1010 V
b11111111111111111111111111111000 1
b1010 8
b1010 ;
bz :
bz R
bz Y
bz \
bz _
bz b
bz e
bz h
bz k
bz n
bz q
bz t
bz w
bz z
bz }
bz ""
bz %"
bz ("
b0 C
b1101 D
b0 ,
b0 I
bz *
bz K
b0 +
b0 J
0&
b11101 7
b11101 =
b11101 F
b11111111111111111111111111111110 2
b11111111111111111111111111111110 +"
b1111111111111110 3
b1111111111111110 H
b1111111111111110 *"
b1 (
b1 M
b1 W
b0 )
b0 L
b0 U
b1 6
b1 >
b1 B
b11010000111111111111111000010000 !
b11010000111111111111111000010000 $
b11010000111111111111111000010000 0
b11010000111111111111111000010000 E
b11010000111111111111111000010000 O
b10010 N
b1000100 9
b1000100 P
b100 Z
b100 .
b100 <
b100 T
b1001000 /
b1001000 Q
1"
#120000
0"
#130000
b1 ?
1X
b110 :
b110 R
b110 Y
b110 \
b110 _
b110 b
b110 e
b110 h
b110 k
b110 n
b110 q
b110 t
b110 w
b110 z
b110 }
b110 ""
b110 %"
b110 ("
b10 *
b10 K
1&
b110 6
b110 >
b110 B
b1000 1
b10 8
b10 ;
b1011 C
b11 D
b1 ,
b1 I
b10 +
b10 J
b11 7
b11 =
b11 F
b10 2
b10 +"
b10 3
b10 H
b10 *"
b0 -
b0 A
b0 V
b10 (
b10 M
b10 W
b111011000000000000001000000000 !
b111011000000000000001000000000 $
b111011000000000000001000000000 0
b111011000000000000001000000000 E
b111011000000000000001000000000 O
b10001 N
b1001000 9
b1001000 P
b1000100 /
b1000100 Q
1"
#140000
0"
#150000
0X
b1010 -
b1010 A
b1010 V
b11111111111111111111111111111000 1
b1010 8
b1010 ;
b0 ?
bz :
bz R
bz Y
bz \
bz _
bz b
bz e
bz h
bz k
bz n
bz q
bz t
bz w
bz z
bz }
bz ""
bz %"
bz ("
b0 C
b1101 D
b0 ,
b0 I
bz *
bz K
b0 +
b0 J
0&
b11101 7
b11101 =
b11101 F
b11111111111111111111111111111110 2
b11111111111111111111111111111110 +"
b1111111111111110 3
b1111111111111110 H
b1111111111111110 *"
b1 (
b1 M
b1 W
b0 )
b0 L
b0 U
b1 6
b1 >
b1 B
b11010000111111111111111000010000 !
b11010000111111111111111000010000 $
b11010000111111111111111000010000 0
b11010000111111111111111000010000 E
b11010000111111111111111000010000 O
b10010 N
b1000100 9
b1000100 P
b110 Z
b110 .
b110 <
b110 T
b1001000 /
b1001000 Q
1"
#160000
0"
#170000
b10 ?
1X
b1000 :
b1000 R
b1000 Y
b1000 \
b1000 _
b1000 b
b1000 e
b1000 h
b1000 k
b1000 n
b1000 q
b1000 t
b1000 w
b1000 z
b1000 }
b1000 ""
b1000 %"
b1000 ("
b10 *
b10 K
1&
b1000 6
b1000 >
b1000 B
b1000 1
b10 8
b10 ;
b1011 C
b11 D
b1 ,
b1 I
b10 +
b10 J
b11 7
b11 =
b11 F
b10 2
b10 +"
b10 3
b10 H
b10 *"
b0 -
b0 A
b0 V
b10 (
b10 M
b10 W
b111011000000000000001000000000 !
b111011000000000000001000000000 $
b111011000000000000001000000000 0
b111011000000000000001000000000 E
b111011000000000000001000000000 O
b10001 N
b1001000 9
b1001000 P
b1000100 /
b1000100 Q
1"
#180000
0"
