verilog/Register.v
module Register(
input clk, reset, en_write,
input[BIT_WIDTH - 1: 0] data_in,
output reg [BIT_WIDTH - 1: 0] data_out
);

parameter BIT_WIDTH = 32;
parameter RESET_VALUE = 0;

always @(posedge clk) begin
    if (reset == 1'b1)
        data_out <= RESET_VALUE;
    else if (en_write == 1'b1)
        data_out <= data_in;
end

endmodule

verilog/testbenches/Register_tb.v
`timescale 1ns/1ps

`include "Register.v"

module Register_tb;

reg clock;
reg reset;
reg en_write;
reg [31:0] data_in;
wire [31:0] data_out;

Register #(
    .BIT_WIDTH(32),
    .RESET_VALUE(0)
    ) regs (
    .clk (clock),
    .reset (reset),
    .en_write (en_write),
    .data_in (data_in),
    .data_out (data_out)
    );

// integer i;
initial begin
    $dumpfile("Register.vcd");
    $dumpvars(0, Register_tb);
end

initial begin
    reset <= 0;
    clock <= 0;
    @(posedge clock);
    reset <= 1;
    @(posedge clock);
    reset <= 0;
    @(posedge clock);

    data_in <= 0;
    en_write <= 0;
    @(posedge clock);
    en_write <= 1;

    @(posedge clock);

    // @(posedge clock);
    // @(posedge clock);
    // @(posedge clock);


    data_in <= 9;
    @(posedge clock);
    @(posedge clock);
    @(posedge clock);

    data_in <= 7;
    @(posedge clock);
    @(posedge clock);
    // en_write = 0;
    data_in <= 8;
    @(posedge clock);
    @(posedge clock);


    $finish;
end

// Create clock
always #1 clock = ~clock;
// initial begin
//     forever begin
//     clock = 0;
//     #5 clock = ~clock;
//     end
// end

endmodule

verilog/testbenches/Register.vcd
$date
	Sat Nov 11 21:58:40 2017
$end
$version
	Icarus Verilog
$end
$timescale
	1ps
$end
$scope module Register_tb $end
$var wire 32 ! data_out [31:0] $end
$var reg 1 " clock $end
$var reg 32 # data_in [31:0] $end
$var reg 1 $ en_write $end
$var reg 1 % reset $end
$scope module regs $end
$var wire 1 " clk $end
$var wire 32 & data_in [31:0] $end
$var wire 1 $ en_write $end
$var wire 1 % reset $end
$var reg 32 ' data_out [31:0] $end
$upscope $end
$upscope $end
$enddefinitions $end
#0
$dumpvars
bx '
bx &
0%
x$
bx #
0"
bx !
$end
#1000
1%
1"
#2000
0"
#3000
0%
b0 !
b0 '
1"
#4000
0"
#5000
0$
b0 #
b0 &
1"
#6000
0"
#7000
1$
1"
#8000
0"
#9000
b1001 #
b1001 &
1"
#10000
0"
#11000
b1001 !
b1001 '
1"
#12000
0"
#13000
1"
#14000
0"
#15000
b111 #
b111 &
1"
#16000
0"
#17000
b111 !
b111 '
1"
#18000
0"
#19000
b1000 #
b1000 &
1"
#20000
0"
#21000
b1000 !
b1000 '
1"
